{
    "word": "angelogen, log an, angelogen",
    "definition": "The term \"angelogen\" refers to the act of intentionally providing false information or deceiving someone through spoken or written communication. It is commonly used to describe situations where someone deliberately lies or tells untruths.",
    "examples": {
        "examples": [
            {
                "german": "Du hast angelogen!",
                "english": "You lied!"
            },
            {
                "german": "Er hat mich angelogen.",
                "english": "He lied to me."
            },
            {
                "german": "Sie hat angelogen, um sich zu schützen.",
                "english": "She lied to protect herself."
            },
            {
                "german": "Warum hast du angelogen?",
                "english": "Why did you lie?"
            },
            {
                "german": "Ich kann nicht glauben, dass er mich angelogen hat.",
                "english": "I can't believe he lied to me."
            }
        ]
    }
}