{
    "word": "das Argument, die Argumente",
    "definition": "A reason or set of reasons presented to support or oppose a point of view, typically used in discussions or debates to persuade or convince others.",
    "examples": [
        {
            "german": "Das ist ein gutes Argument.",
            "english": "That is a good argument."
        },
        {
            "german": "Er hat viele Argumente vorgebracht.",
            "english": "He presented many arguments."
        },
        {
            "german": "Das Argument ist nicht überzeugend.",
            "english": "The argument is not convincing."
        },
        {
            "german": "Sie hat ein starkes Argument geliefert.",
            "english": "She provided a strong argument."
        },
        {
            "german": "Das Argument ist logisch.",
            "english": "The argument is logical."
        }
    ]
}