{
    "word": "die Auflage, die Die auflagen",
    "definition": "A term commonly used to describe a specific requirement or condition that must be fulfilled in order to proceed with a particular task or activity. It is often associated with legal or regulatory contexts, where it denotes a mandatory provision or stipulation that needs to be met. Additionally, it can refer to a print run or edition of a publication, typically used in the context of books, newspapers, or magazines.",
    "examples": [
        {
            "german": "Die Zeitung hat eine Auflage von 100.000 Exemplaren.",
            "english": "The newspaper has a circulation of 100,000 copies."
        },
        {
            "german": "Die Zeitschrift hat eine Auflage von 50.000 Stück.",
            "english": "The magazine has a print run of 50,000 copies."
        },
        {
            "german": "Die erste Auflage des Buches war innerhalb einer Woche ausverkauft.",
            "english": "The first edition of the book sold out within a week."
        },
        {
            "german": "Die Auflage der Briefmarken beträgt 1 Million.",
            "english": "The print run of the stamps is 1 million."
        },
        {
            "german": "Die limitierte Auflage des Sammlerstücks ist bereits vergriffen.",
            "english": "The limited edition of the collector's item is already sold out."
        }
    ]
}