{
    "word": "der Aufruhr, die Aufruhr",
    "definition": "A state of disorder or unrest characterized by public disturbances, protests, or rebellious actions, often involving a large number of people. It is typically used to describe a situation where there is a significant level of social or political upheaval, often resulting from dissatisfaction or grievances within a society.",
    "examples": [
        {
            "german": "Es herrschte Aufruhr in der Stadt.",
            "english": "There was turmoil in the city."
        },
        {
            "german": "Der politische Aufruhr führte zu Unruhen.",
            "english": "The political unrest led to riots."
        },
        {
            "german": "Die Menschen protestierten gegen den Aufruhr der Regierung.",
            "english": "People protested against the government's upheaval."
        },
        {
            "german": "Der Aufruhr wurde gewaltsam niedergeschlagen.",
            "english": "The uprising was violently suppressed."
        },
        {
            "german": "Der Aufruhr breitete sich schnell im ganzen Land aus.",
            "english": "The turmoil spread rapidly throughout the country."
        }
    ]
}