{
    "word": "die Bundesliga, die Die bundesligen",
    "definition": "The term refers to the top professional football league in Germany, consisting of multiple teams competing against each other in a season-long tournament. It is commonly used to describe the highest level of football competition in the country, attracting significant attention from fans and media alike.",
    "examples": [
        {
            "german": "Die Bundesliga ist die höchste Spielklasse im deutschen Fußball.",
            "english": "The Bundesliga is the highest division in German football."
        },
        {
            "german": "Der FC Bayern München ist der Rekordmeister der Bundesliga.",
            "english": "FC Bayern Munich is the record champion of the Bundesliga."
        },
        {
            "german": "Die Bundesliga wurde 1963 gegründet.",
            "english": "The Bundesliga was founded in 1963."
        },
        {
            "german": "Die Bundesliga besteht aus 18 Mannschaften.",
            "english": "The Bundesliga consists of 18 teams."
        },
        {
            "german": "Die Bundesliga-Saison dauert in der Regel von August bis Mai.",
            "english": "The Bundesliga season usually lasts from August to May."
        }
    ]
}