{
    "word": "die Butter, die Die butter",
    "definition": "A creamy, spreadable substance made from churning milk or cream, typically used as a condiment or ingredient in cooking and baking. It is commonly spread on bread, used in baking recipes, or melted for cooking purposes.",
    "examples": [
        {
            "german": "Ich esse gerne Butter auf meinem Brot.",
            "english": "I like to eat butter on my bread."
        },
        {
            "german": "Die Butter ist im Kühlschrank.",
            "english": "The butter is in the fridge."
        },
        {
            "german": "Kannst du bitte Butter vom Supermarkt mitbringen?",
            "english": "Can you please bring butter from the supermarket?"
        },
        {
            "german": "Die Butter ist zu hart, um sie zu streichen.",
            "english": "The butter is too hard to spread."
        },
        {
            "german": "Butter wird aus Milch hergestellt.",
            "english": "Butter is made from milk."
        }
    ]
}