{
    "word": "der Dolmetscher, die Dolmetscher",
    "definition": "A professional who facilitates communication between individuals who speak different languages, typically employed in settings such as conferences, meetings, or legal proceedings.",
    "examples": [
        {
            "german": "Ich brauche einen Dolmetscher für die Konferenz.",
            "english": "I need an interpreter for the conference."
        },
        {
            "german": "Der Dolmetscher übersetzte die Rede simultan.",
            "english": "The interpreter translated the speech simultaneously."
        },
        {
            "german": "Mein Freund arbeitet als Dolmetscher bei den Vereinten Nationen.",
            "english": "My friend works as an interpreter at the United Nations."
        },
        {
            "german": "Der Dolmetscher half den beiden Parteien, sich zu verständigen.",
            "english": "The interpreter helped the two parties communicate."
        },
        {
            "german": "Die Dolmetscherin beherrscht mehrere Sprachen fließend.",
            "english": "The female interpreter is fluent in multiple languages."
        }
    ]
}