{
    "word": "der Eichel, die Eicheln",
    "definition": "A small, rounded, and typically brown object that is often found in forests and is associated with trees. It is commonly used in various crafts and can be collected as a natural curiosity.",
    "examples": [
        {
            "german": "Die Eichel ist die Frucht der Eiche.",
            "english": "The acorn is the fruit of the oak tree."
        },
        {
            "german": "Die Eichel dient als Nahrung für Eichhörnchen.",
            "english": "Acorns serve as food for squirrels."
        },
        {
            "german": "Die Eichel wird im Herbst von den Bäumen fallen.",
            "english": "The acorns will fall from the trees in autumn."
        },
        {
            "german": "Die Eichel hat eine harte Schale.",
            "english": "The acorn has a hard shell."
        },
        {
            "german": "Eicheln können zu Mehl gemahlen werden.",
            "english": "Acorns can be ground into flour."
        }
    ]
}