{
    "word": "erholen, erholte, erholt",
    "definition": "To regain strength, energy, or well-being after physical or mental exertion, often by resting, relaxing, or engaging in leisure activities. It is commonly used to describe the process of recovering or recuperating from fatigue, stress, or illness.",
    "examples": [
        {
            "german": "Ich muss mich erholen.",
            "english": "I need to relax."
        },
        {
            "german": "Sie erholen sich am Strand.",
            "english": "They are relaxing at the beach."
        },
        {
            "german": "Nach dem Training erhole ich mich gerne in der Sauna.",
            "english": "After the workout, I like to relax in the sauna."
        },
        {
            "german": "Erhol dich gut!",
            "english": "Have a good rest!"
        },
        {
            "german": "Die Natur hilft uns, uns zu erholen.",
            "english": "Nature helps us to recover."
        }
    ]
}