{
    "word": "erleichtern, erleichterte, erleichtert",
    "definition": "To make a burden or task less difficult or heavy, providing relief or ease. This verb is commonly used when referring to the process of lightening or alleviating someone's emotional or physical load, typically by offering assistance, support, or comfort.",
    "examples": [
        {
            "german": "Ich möchte Ihnen die Arbeit erleichtern.",
            "english": "I want to make your work easier."
        },
        {
            "german": "Die neue Software erleichtert die Datenverwaltung.",
            "english": "The new software simplifies data management."
        },
        {
            "german": "Eine gute Planung kann den Umzug erleichtern.",
            "english": "Good planning can facilitate the move."
        },
        {
            "german": "Die Übersichtlichkeit der Webseite erleichtert die Navigation.",
            "english": "The clarity of the website facilitates navigation."
        },
        {
            "german": "Ein gutes Training kann das Lernen erleichtern.",
            "english": "Good training can make learning easier."
        }
    ]
}