{
    "word": "die Fernbeziehung, die Fernbeziehungen",
    "definition": "A romantic relationship between two individuals who live in separate geographical locations, often implying a significant physical distance between them. This term is commonly used to describe relationships where the partners reside in different cities, countries, or even continents, requiring them to maintain the connection primarily through communication technology and occasional visits.",
    "examples": [
        {
            "german": "Wir führen eine Fernbeziehung.",
            "english": "We are in a long-distance relationship."
        },
        {
            "german": "Die Entfernung macht unsere Fernbeziehung schwierig.",
            "english": "The distance makes our long-distance relationship difficult."
        },
        {
            "german": "Sie haben eine erfolgreiche Fernbeziehung geführt.",
            "english": "They had a successful long-distance relationship."
        },
        {
            "german": "Eine Fernbeziehung erfordert viel Vertrauen.",
            "english": "A long-distance relationship requires a lot of trust."
        },
        {
            "german": "Sie haben sich entschieden, ihre Fernbeziehung zu beenden.",
            "english": "They decided to end their long-distance relationship."
        }
    ]
}