{
    "word": "der Fluß, die Flüsse",
    "definition": "A natural watercourse, typically flowing towards an ocean, sea, lake, or another river, often used to refer to a large and significant body of flowing water. It is commonly used in geographical and environmental contexts, and can also be associated with various cultural and historical references.",
    "examples": [
        {
            "german": "Der Rhein ist ein großer Fluss in Deutschland.",
            "english": "The Rhine is a large river in Germany."
        },
        {
            "german": "Der Amazonas ist der längste Fluss der Welt.",
            "english": "The Amazon is the longest river in the world."
        },
        {
            "german": "Viele Städte wurden entlang des Flusses gebaut.",
            "english": "Many cities were built along the river."
        },
        {
            "german": "Der Fluss fließt durch malerische Landschaften.",
            "english": "The river flows through picturesque landscapes."
        },
        {
            "german": "Die Kinder spielen am Ufer des Flusses.",
            "english": "The children play on the riverbank."
        }
    ]
}