{
    "word": "die Flüssigkeit, die Flüssigkeiten",
    "definition": "A substance that is not solid and can flow, typically taking the shape of its container. It is commonly used to describe substances like water, juice, oil, and other liquids.",
    "examples": [
        {
            "german": "Wasser ist eine Flüssigkeit.",
            "english": "Water is a liquid."
        },
        {
            "german": "Die Flüssigkeit tropfte langsam aus der Flasche.",
            "english": "The liquid dripped slowly from the bottle."
        },
        {
            "german": "Die Flüssigkeit hat eine bläuliche Farbe.",
            "english": "The liquid has a bluish color."
        },
        {
            "german": "Die Flüssigkeit ist giftig.",
            "english": "The liquid is toxic."
        },
        {
            "german": "Die Flüssigkeit verdampft bei hoher Temperatur.",
            "english": "The liquid evaporates at high temperature."
        }
    ]
}