{
    "word": "folgsam",
    "definition": "The term \"folgsam\" refers to a quality or characteristic of a person or thing that is compliant, obedient, or easily influenced by others. It is commonly used to describe individuals who are inclined to follow instructions, rules, or orders without resistance or hesitation.",
    "examples": [
        {
            "german": "Sie ist sehr folgsam und tut immer, was man ihr sagt.",
            "english": "She is very obedient and always does what she is told."
        },
        {
            "german": "Der Hund ist sehr folgsam und hört auf jedes Kommando.",
            "english": "The dog is very obedient and follows every command."
        },
        {
            "german": "Die Schülerin ist sehr folgsam und macht immer ihre Hausaufgaben.",
            "english": "The student is very obedient and always does her homework."
        },
        {
            "german": "Der Roboter ist sehr folgsam und erledigt alle Aufgaben.",
            "english": "The robot is very obedient and completes all tasks."
        },
        {
            "german": "Er ist ein folgsamer Angestellter und erfüllt alle Anweisungen.",
            "english": "He is a obedient employee and fulfills all instructions."
        }
    ]
}