{
    "word": "die Getreideernte, die Getreideernten",
    "definition": "The term refers to the process of gathering a specific agricultural product, typically associated with the cultivation and harvesting of a particular crop. It commonly denotes the collection of a staple food source, often used for human consumption or animal feed.",
    "examples": [
        {
            "german": "Die Getreideernte war in diesem Jahr besonders gut.",
            "english": "The grain harvest was particularly good this year."
        },
        {
            "german": "Die Getreideernte ist eine wichtige landwirtschaftliche Tätigkeit.",
            "english": "Grain harvest is an important agricultural activity."
        },
        {
            "german": "Die Getreideernte erfolgt normalerweise im Sommer.",
            "english": "Grain harvest usually takes place in the summer."
        },
        {
            "german": "Die Getreideernte wird maschinell durchgeführt.",
            "english": "Grain harvest is carried out mechanically."
        },
        {
            "german": "Die Getreideernte ist von großer wirtschaftlicher Bedeutung.",
            "english": "Grain harvest is of great economic importance."
        }
    ]
}