{
    "word": "das Gitterbett, die Gitterbetten",
    "definition": "A type of furniture designed for infants or young children, typically consisting of a frame with bars or slats on the sides and ends to prevent the child from falling out. It is commonly used in nurseries or children's bedrooms for safety and security during sleep or rest.",
    "examples": [
        {
            "german": "Das Baby schläft im Gitterbett.",
            "english": "The baby sleeps in the crib."
        },
        {
            "german": "Wir haben ein Gitterbett für unser Kind gekauft.",
            "english": "We bought a crib for our child."
        },
        {
            "german": "Das Gitterbett ist aus Holz.",
            "english": "The crib is made of wood."
        },
        {
            "german": "Das Gitterbett hat eine verstellbare Matratzenhöhe.",
            "english": "The crib has an adjustable mattress height."
        },
        {
            "german": "Das Gitterbett hat ein niedliches Design.",
            "english": "The crib has a cute design."
        }
    ]
}