{
    "word": "die Literatur, die Die literatur",
    "definition": "The body of written works, including novels, poems, plays, and essays, that are considered to have artistic or intellectual value. It encompasses a wide range of creative and intellectual expressions in written form, often reflecting cultural, historical, or social aspects. It is commonly studied, analyzed, and appreciated as a form of artistic expression and cultural heritage.",
    "examples": [
        {
            "german": "Die deutsche Literatur ist sehr vielfältig.",
            "english": "German literature is very diverse."
        },
        {
            "german": "Ich habe eine Vorliebe für klassische Literatur.",
            "english": "I have a preference for classical literature."
        },
        {
            "german": "Die Literatur des 19. Jahrhunderts ist besonders interessant.",
            "english": "The literature of the 19th century is particularly interesting."
        },
        {
            "german": "Er hat einen Doktor in Literaturwissenschaften.",
            "english": "He has a doctorate in literature."
        },
        {
            "german": "Die Literatur beeinflusst unsere Denkweise und Kultur.",
            "english": "Literature influences our way of thinking and culture."
        }
    ]
}