{
    "word": "die Lotterie, die Die lotterien",
    "definition": "A game of chance where participants purchase tickets in the hopes of winning a prize, typically involving a random drawing or selection process. It is commonly used to refer to a form of gambling or a lottery.",
    "examples": [
        {
            "german": "Ich habe bei der Lotterie gewonnen.",
            "english": "I won the lottery."
        },
        {
            "german": "Die Lotterie zieht jeden Samstag die Gewinnzahlen.",
            "english": "The lottery draws the winning numbers every Saturday."
        },
        {
            "german": "Er hat sein ganzes Geld für Lotterielose ausgegeben.",
            "english": "He spent all his money on lottery tickets."
        },
        {
            "german": "Die Lotterie unterstützt wohltätige Zwecke.",
            "english": "The lottery supports charitable causes."
        },
        {
            "german": "Die Lotterie bietet hohe Gewinnchancen.",
            "english": "The lottery offers high chances of winning."
        }
    ]
}