{
    "word": "modern",
    "definition": "A term commonly employed to describe something that is characterized by contemporary or up-to-date qualities, often associated with current trends, styles, or technologies. It is frequently used to refer to objects, ideas, or artistic expressions that reflect a departure from traditional or outdated conventions, embracing a more progressive and innovative approach.",
    "examples": [
        {
            "german": "Das moderne Haus hat große Fenster.",
            "english": "The modern house has large windows."
        },
        {
            "german": "Sie trägt immer moderne Kleidung.",
            "english": "She always wears modern clothes."
        },
        {
            "german": "Die moderne Technologie hat unser Leben verändert.",
            "english": "Modern technology has changed our lives."
        },
        {
            "german": "Er ist ein moderner Künstler.",
            "english": "He is a modern artist."
        },
        {
            "german": "Das moderne Design des Autos gefällt mir.",
            "english": "I like the modern design of the car."
        }
    ]
}