{
    "word": "der Müllcontainer, die Die müllcontainer",
    "definition": "A receptacle typically found outdoors, often made of metal or plastic, used for the containment and disposal of waste materials. It is commonly found in public spaces, residential areas, and commercial establishments.",
    "examples": [
        {
            "german": "Der Müllcontainer steht hinter dem Haus.",
            "english": "The trash container is behind the house."
        },
        {
            "german": "Bitte werfen Sie den Müll in den Müllcontainer.",
            "english": "Please throw the trash into the trash container."
        },
        {
            "german": "Der Müllcontainer wird einmal pro Woche geleert.",
            "english": "The trash container is emptied once a week."
        },
        {
            "german": "Der Müllcontainer ist überfüllt.",
            "english": "The trash container is overflowing."
        },
        {
            "german": "Der Müllcontainer ist für Haushaltsabfälle vorgesehen.",
            "english": "The trash container is intended for household waste."
        }
    ]
}