{
    "word": "der Parkranger, die Parkranger",
    "definition": "A person who works in a protected natural area, responsible for maintaining its conservation, enforcing regulations, and ensuring the safety and well-being of visitors. They typically patrol the park, provide information to visitors, and may also participate in wildlife management and rescue operations.",
    "examples": [
        {
            "german": "Der Parkranger patrouilliert regelmäßig durch den Nationalpark.",
            "english": "The park ranger patrols the national park regularly."
        },
        {
            "german": "Der Parkranger kümmert sich um den Schutz der Tier- und Pflanzenwelt.",
            "english": "The park ranger takes care of the protection of the wildlife and plants."
        },
        {
            "german": "Der Parkranger informiert die Besucher über die Regeln im Park.",
            "english": "The park ranger informs the visitors about the rules in the park."
        },
        {
            "german": "Der Parkranger führt Wandergruppen durch den Wald.",
            "english": "The park ranger guides hiking groups through the forest."
        },
        {
            "german": "Der Parkranger sorgt für die Sicherheit der Besucher.",
            "english": "The park ranger ensures the safety of the visitors."
        }
    ]
}