{
    "word": "pünktlich",
    "definition": "Adhering strictly to scheduled times or being punctual; typically used to describe someone's timeliness or the promptness of an event or action.",
    "examples": {
        "examples": [
            {
                "german": "Er kommt immer pünktlich zur Arbeit.",
                "english": "He always comes to work on time."
            },
            {
                "german": "Der Zug ist pünktlich abgefahren.",
                "english": "The train left on time."
            },
            {
                "german": "Sie ist bekannt für ihre pünktliche Art.",
                "english": "She is known for her punctuality."
            },
            {
                "german": "Bitte sei pünktlich zum Treffen.",
                "english": "Please be on time for the meeting."
            },
            {
                "german": "Die Veranstaltung beginnt pünktlich um 19 Uhr.",
                "english": "The event starts promptly at 7 PM."
            }
        ]
    }
}