{
    "word": "das Quartal, die Quartale",
    "definition": "A unit of time commonly used in business and finance to refer to a specific period of three consecutive months. It is often utilized for reporting financial results, analyzing market trends, and evaluating performance.",
    "examples": [
        {
            "german": "Das Unternehmen veröffentlichte seine Quartalszahlen.",
            "english": "The company released its quarterly figures."
        },
        {
            "german": "Der Umsatz stieg im letzten Quartal um 10 Prozent.",
            "english": "Revenue increased by 10 percent in the last quarter."
        },
        {
            "german": "Das Quartal endet am 31. März.",
            "english": "The quarter ends on March 31st."
        },
        {
            "german": "Die Firma plant, im nächsten Quartal neue Produkte einzuführen.",
            "english": "The company plans to introduce new products in the next quarter."
        },
        {
            "german": "Der Gewinn im dritten Quartal übertraf die Erwartungen der Analysten.",
            "english": "The profit in the third quarter exceeded analysts' expectations."
        }
    ]
}