{
    "word": "ruinieren, ruinierte, ruiniert",
    "definition": "To cause severe damage or destruction to someone's financial situation, plans, or reputation, often resulting in their downfall or failure. This term is commonly used to describe actions that lead to the ruin or bankruptcy of individuals, businesses, or projects.",
    "examples": [
        {
            "german": "Er hat sein ganzes Vermögen ruiniert.",
            "english": "He has ruined his entire fortune."
        },
        {
            "german": "Die schlechte Wirtschaftslage hat das Unternehmen ruiniert.",
            "english": "The poor economic situation has ruined the company."
        },
        {
            "german": "Der Sturm hat das Haus komplett ruiniert.",
            "english": "The storm has completely ruined the house."
        },
        {
            "german": "Seine schlechten Entscheidungen haben seine Karriere ruiniert.",
            "english": "His bad decisions have ruined his career."
        },
        {
            "german": "Die falsche Diät hat ihre Gesundheit ruiniert.",
            "english": "The wrong diet has ruined her health."
        }
    ]
}