{
    "word": "die Schadensursache, die Die schadensursachen",
    "definition": "A term used to describe the primary reason or factor that leads to damage, harm, or loss. It is commonly employed in legal, insurance, or investigative contexts to identify and determine the cause of an adverse event or accident.",
    "examples": [
        {
            "german": "Die Schadensursache des Unfalls war ein technischer Defekt.",
            "english": "The cause of the accident was a technical defect."
        },
        {
            "german": "Die Schadensursache des Brandes ist noch unklar.",
            "english": "The cause of the fire is still unknown."
        },
        {
            "german": "Die Schadensursache des Wasserschadens war ein Rohrbruch.",
            "english": "The cause of the water damage was a pipe burst."
        },
        {
            "german": "Die Schadensursache des Diebstahls konnte nicht ermittelt werden.",
            "english": "The cause of the theft could not be determined."
        },
        {
            "german": "Die Schadensursache des Sturmschadens war der starke Wind.",
            "english": "The cause of the storm damage was the strong wind."
        }
    ]
}