{
    "word": "schmackhaft",
    "definition": "The term \"schmackhaft\" refers to something that possesses an appealing taste or flavor, often described as delicious or savory. It is commonly used to describe food or dishes that are enjoyable to eat due to their palatability.",
    "examples": [
        {
            "german": "Dieses Gericht ist sehr schmackhaft.",
            "english": "This dish is very tasty."
        },
        {
            "german": "Die Schokolade schmeckt schmackhaft.",
            "english": "The chocolate tastes delicious."
        },
        {
            "german": "Das Essen im Restaurant war schmackhaft.",
            "english": "The food at the restaurant was flavorful."
        },
        {
            "german": "Die Suppe ist schmackhaft und würzig.",
            "english": "The soup is tasty and flavorful."
        },
        {
            "german": "Die schmackhaften Kekse wurden schnell aufgegessen.",
            "english": "The delicious cookies were quickly eaten."
        }
    ]
}