{
    "word": "der Standpunkt, die Standpunkte",
    "definition": "A perspective or viewpoint on a particular matter, often used to express one's opinion or stance on a topic. It is commonly employed in discussions, debates, or arguments to convey a specific position or belief.",
    "examples": [
        {
            "german": "Ich habe einen anderen Standpunkt.",
            "english": "I have a different point of view."
        },
        {
            "german": "Er vertritt einen radikalen Standpunkt.",
            "english": "He holds a radical standpoint."
        },
        {
            "german": "Wir müssen unseren Standpunkt klar machen.",
            "english": "We need to make our position clear."
        },
        {
            "german": "Sie hat einen festen Standpunkt zu diesem Thema.",
            "english": "She has a strong standpoint on this issue."
        },
        {
            "german": "Sein Standpunkt ist nicht leicht zu verstehen.",
            "english": "His point of view is not easy to understand."
        }
    ]
}