{
    "word": "stärken, stärkte, gestärkt",
    "definition": "To reinforce or fortify something, typically used in the context of enhancing or strengthening a particular aspect, quality, or attribute.",
    "examples": [
        {
            "german": "Ich möchte meine Stärken nutzen.",
            "english": "I want to use my strengths."
        },
        {
            "german": "Sie hat ihre Stärken erkannt.",
            "english": "She has recognized her strengths."
        },
        {
            "german": "Die Übung soll die Muskeln stärken.",
            "english": "The exercise is meant to strengthen the muscles."
        },
        {
            "german": "Er versucht, seine Position zu stärken.",
            "english": "He is trying to strengthen his position."
        },
        {
            "german": "Die Therapie soll das Immunsystem stärken.",
            "english": "The therapy is meant to strengthen the immune system."
        }
    ]
}