{
    "word": "der Treffpunkt, die Treffpunkte",
    "definition": "A designated location or place where individuals arrange to meet, typically used to refer to a specific meeting point for social gatherings, appointments, or planned events.",
    "examples": [
        {
            "german": "Der Treffpunkt ist vor dem Kino.",
            "english": "The meeting point is in front of the cinema."
        },
        {
            "german": "Wir haben einen Treffpunkt vereinbart.",
            "english": "We have arranged a meeting point."
        },
        {
            "german": "Der Treffpunkt ist leicht zu finden.",
            "english": "The meeting point is easy to find."
        },
        {
            "german": "Der Treffpunkt wurde geändert.",
            "english": "The meeting point has been changed."
        },
        {
            "german": "Der Treffpunkt ist um 18 Uhr.",
            "english": "The meeting point is at 6 PM."
        }
    ]
}