{
    "word": "vorlegen, legte vor, vorgelegt",
    "definition": "To present or submit something for examination, consideration, or approval, often in a formal or official context. It is commonly used in professional or academic settings, where documents, reports, or proposals are typically \"vorlegen\" to supervisors, committees, or authorities for review or assessment.",
    "examples": [
        {
            "german": "Kannst du mir bitte deinen Ausweis vorlegen?",
            "english": "Can you please show me your ID?"
        },
        {
            "german": "Der Arzt wird Ihnen eine Rechnung vorlegen.",
            "english": "The doctor will present you with a bill."
        },
        {
            "german": "Sie müssen Ihre Bewerbungsunterlagen vorlegen.",
            "english": "You need to submit your application documents."
        },
        {
            "german": "Kannst du mir das Buch vorlegen?",
            "english": "Can you show me the book?"
        },
        {
            "german": "Der Kellner wird Ihnen die Speisekarte vorlegen.",
            "english": "The waiter will hand you the menu."
        }
    ]
}