{
    "word": "der Wassergehalt, die Wassergehalte",
    "definition": "The measurement of the amount of water present in a substance, typically used to describe the moisture content of a material or product.",
    "examples": [
        {
            "german": "Der Wassergehalt des Bodens ist zu hoch.",
            "english": "The water content of the soil is too high."
        },
        {
            "german": "Die Wassergehalte der verschiedenen Lebensmittel variieren stark.",
            "english": "The water contents of the different foods vary greatly."
        },
        {
            "german": "Der Wassergehalt in der Luft beeinflusst das Klima.",
            "english": "The water content in the air affects the climate."
        },
        {
            "german": "Der Wassergehalt eines Produkts kann Auswirkungen auf seine Haltbarkeit haben.",
            "english": "The water content of a product can have an impact on its shelf life."
        },
        {
            "german": "Der Wassergehalt im Körper ist wichtig für die Aufrechterhaltung der Gesundheit.",
            "english": "The water content in the body is important for maintaining health."
        }
    ]
}