{
    "word": "wie",
    "definition": "The word \"wie\" is commonly used to compare or inquire about similarities between two or more things, actions, or concepts. It is often employed to ask questions about manner, method, or way of doing something. Additionally, \"wie\" can be used to express surprise or disbelief when used in certain contexts.",
    "examples": {
        "examples": [
            {
                "german": "Wie geht es dir?",
                "english": "How are you?"
            },
            {
                "german": "Wie alt bist du?",
                "english": "How old are you?"
            },
            {
                "german": "Wie viel kostet das?",
                "english": "How much does it cost?"
            },
            {
                "german": "Wie spät ist es?",
                "english": "What time is it?"
            },
            {
                "german": "Wie heißt du?",
                "english": "What is your name?"
            }
        ]
    }
}