{
    "word": "wittern, witterte, gewittert",
    "definition": "To perceive or sense something through the olfactory sense, often used to describe the act of animals detecting scents in their environment.",
    "examples": [
        {
            "german": "Ich wittere Gefahr.",
            "english": "I sense danger."
        },
        {
            "german": "Der Hund wittert eine Spur.",
            "english": "The dog sniffs a trail."
        },
        {
            "german": "Sie konnte den Erfolg schon wittern.",
            "english": "She could already smell success."
        },
        {
            "german": "Er wittert eine Verschwörung.",
            "english": "He suspects a conspiracy."
        },
        {
            "german": "Die Katze wittert eine Maus.",
            "english": "The cat scents a mouse."
        }
    ]
}