{
    "word": "der Zeuge, die Zeugen",
    "definition": "A person who has firsthand knowledge or has observed an event, incident, or situation, and is capable of providing testimony or evidence about it, particularly in a legal context. This term is commonly used to refer to someone who can testify or bear witness to an occurrence, often in a court of law or during an investigation.",
    "examples": [
        {
            "german": "Er war Zeuge des Unfalls.",
            "english": "He was a witness to the accident."
        },
        {
            "german": "Die Polizei sucht nach Zeugen.",
            "english": "The police are looking for witnesses."
        },
        {
            "german": "Der Zeuge sagte vor Gericht aus.",
            "english": "The witness testified in court."
        },
        {
            "german": "Sie ist eine zuverlässige Zeugin.",
            "english": "She is a reliable witness."
        },
        {
            "german": "Der Zeuge identifizierte den Täter.",
            "english": "The witness identified the perpetrator."
        }
    ]
}