{
    "word": "zusammensetzen, setzte zusammen, zusammengesetzt",
    "definition": "To combine or assemble different elements or parts together to form a whole, often referring to the process of constructing or putting together something. This term is commonly used when referring to the act of joining or connecting various components or pieces to create a unified structure or object.",
    "examples": [
        {
            "german": "Ich setze das Puzzle zusammen.",
            "english": "I am putting the puzzle together."
        },
        {
            "german": "Wir müssen die Möbel zusammensetzen.",
            "english": "We need to assemble the furniture."
        },
        {
            "german": "Kannst du den Satz aus den Wörtern zusammensetzen?",
            "english": "Can you construct the sentence from the words?"
        },
        {
            "german": "Die Mannschaft setzt sich aus Spielern verschiedener Nationalitäten zusammen.",
            "english": "The team is composed of players from different nationalities."
        },
        {
            "german": "Er kann sich aus den vorhandenen Materialien ein Modell zusammensetzen.",
            "english": "He can build a model from the available materials."
        }
    ]
}