{
    "word": "übermitteln, übermittelte, übermittelt",
    "definition": "To convey or transmit information, messages, or data from one person or place to another, typically through various means of communication. It is commonly used in the context of sending or delivering information, whether it be through verbal, written, or electronic means.",
    "examples": [
        {
            "german": "Ich werde dir die Informationen übermitteln.",
            "english": "I will transmit the information to you."
        },
        {
            "german": "Bitte übermitteln Sie uns Ihre Kontaktdaten.",
            "english": "Please provide us with your contact information."
        },
        {
            "german": "Die Nachricht wurde erfolgreich übermittelt.",
            "english": "The message was successfully transmitted."
        },
        {
            "german": "Er konnte seine Gedanken nicht richtig übermitteln.",
            "english": "He couldn't convey his thoughts properly."
        },
        {
            "german": "Die Daten werden verschlüsselt übermittelt.",
            "english": "The data is transmitted encrypted."
        }
    ]
}