{
    "word": "die Überlastung, die Die überlastungen",
    "definition": "A state of excessive strain or burden on a system, often resulting from an overwhelming amount of work, responsibilities, or demands. It is commonly used to describe the condition of being overloaded or overwhelmed, particularly in the context of mental or physical stress.",
    "examples": [
        {
            "german": "Die Überlastung des Servers führte zu einem Ausfall.",
            "english": "The server overload led to a failure."
        },
        {
            "german": "Die Überlastung der Autobahn führte zu einem Stau.",
            "english": "The highway congestion caused a traffic jam."
        },
        {
            "german": "Die Überlastung der Mitarbeiter führte zu einer hohen Fehlerquote.",
            "english": "The employees' overload resulted in a high error rate."
        },
        {
            "german": "Die Überlastung des Netzes führte zu einer langsamen Internetverbindung.",
            "english": "The network overload resulted in a slow internet connection."
        },
        {
            "german": "Die Überlastung des Körpers führte zu Erschöpfung.",
            "english": "The body's overload led to exhaustion."
        }
    ]
}